Metadata-Version: 2.4
Name: setup_baizhanMath02
Version: 1.1
Summary: 测试第一个对外发布模块
Author: zhoutongtong
Author-email: 2311522765@qq.com
Dynamic: author
Dynamic: author-email
Dynamic: summary
